MANIFEST.in
README.rst
setup.cfg
setup.py
sphinxcontrib/__init__.py
sphinxcontrib/autorun.py
sphinxcontrib/pycon.py
sphinxcontrib_autorun.egg-info/PKG-INFO
sphinxcontrib_autorun.egg-info/SOURCES.txt
sphinxcontrib_autorun.egg-info/dependency_links.txt
sphinxcontrib_autorun.egg-info/namespace_packages.txt
sphinxcontrib_autorun.egg-info/not-zip-safe
sphinxcontrib_autorun.egg-info/requires.txt
sphinxcontrib_autorun.egg-info/top_level.txt