Metadata-Version: 1.0
Name: sphinxcontrib-autorun
Version: 0.1-20140415
Summary: Sphinx extension autorun
Home-page: http://bitbucket.org/birkenfeld/sphinx-contrib
Author: Vadim Gubergrits
Author-email: vadim.gubergrits@gmail.com
License: BSD
Download-URL: http://pypi.python.org/pypi/autorun
Platform: any
Classifier: Development Status :: 4 - Beta
Classifier: Environment :: Console
Classifier: Environment :: Web Environment
Classifier: Intended Audience :: Developers
Classifier: License :: OSI Approved :: BSD License
Classifier: Operating System :: OS Independent
Classifier: Programming Language :: Python
Classifier: Topic :: Documentation
Classifier: Topic :: Utilities
